__init__.py
detection_moving_mnist/__init__.py
detection_moving_mnist/mmnist/__init__.py
detection_moving_mnist/mmnist/mmnist.py
detection_moving_mnist/mmnist/trajectory.py
detection_moving_mnist/utils/__init__.py
detection_moving_mnist/utils/utils.py
detection_moving_mnist-0.4.2.dist-info/licenses/LICENSE
detection_moving_mnist-0.4.2.dist-info/METADATA
detection_moving_mnist-0.4.2.dist-info/WHEEL
detection_moving_mnist-0.4.2.dist-info/top_level.txt
detection_moving_mnist-0.4.2.dist-info/RECORD
