Metadata-Version: 2.4
Name: detection_moving_mnist
Version: 0.4.2
Summary: A Moving MNIST dataset generator for object detection tasks.
Author-email: Max Ploter <maksim.ploter@gmail.com>
Project-URL: Homepage, https://github.com/maxploter/detection-moving-mmnist
Project-URL: Issues, https://github.com/maxploter/detection-moving-mmnist/issues
Classifier: Programming Language :: Python :: 3
Classifier: Operating System :: OS Independent
Classifier: License :: OSI Approved :: MIT License
Requires-Python: >=3.8
License-File: LICENSE
Dynamic: license-file
